pydoctrace/__init__.py
pydoctrace/callfilter/__init__.py
pydoctrace/callfilter/presets.py
pydoctrace/doctrace.py
pydoctrace/domain/diagram.py
pydoctrace/domain/execution.py
pydoctrace/exporters/__init__.py
pydoctrace/exporters/formatters.py
pydoctrace/exporters/plantuml/__init__.py
pydoctrace/exporters/plantuml/component.py
pydoctrace/exporters/plantuml/sequence.py
pydoctrace/tracer.py
pydoctrace-0.3.0.dist-info/LICENSE
pydoctrace-0.3.0.dist-info/METADATA
pydoctrace-0.3.0.dist-info/WHEEL
pydoctrace-0.3.0.dist-info/RECORD
