Metadata-Version: 2.1
Name: pydoctrace
Version: 0.3.0
Summary: Generate sequence diagrams by tracing Python code execution
Home-page: https://github.com/lucsorel/pydoctrace
License: MIT
Keywords: sequence diagram,component diagram,documentation,tracing,doc-as-code,PlantUML
Author: Luc Sorel-Giffo
Maintainer: Luc Sorel-Giffo
Requires-Python: >=3.8,<4.0
Classifier: License :: OSI Approved :: MIT License
Classifier: Programming Language :: Python :: 3
Classifier: Programming Language :: Python :: 3.8
Classifier: Programming Language :: Python :: 3.9
Classifier: Programming Language :: Python :: 3.10
Classifier: Programming Language :: Python :: 3.11
Classifier: Programming Language :: Python :: 3.12
Project-URL: Repository, https://github.com/lucsorel/pydoctrace
